[
  {
    "title": "\ud83c\udf1f Wicked AI: Relevez les d\u00e9fis de demain dans un monde BANI \ud83c\udf1f",
    "date": "2024-11-07T18:30:00",
    "url": "https://www.meetup.com/seriousgamers-bordeaux/events/304141350/",
    "description": "L\u2019IA n\u2019est pas seulement une technologie r\u00e9volutionnaire, elle transforme d\u00e9j\u00e0 nos m\u00e9tiers, nos interactions, et m\u00eame nos modes de pens\u00e9e. Mais dans un monde BANI \u2013 Fragile, Anxieux, Non-lin\u00e9aire, Incompr\u00e9hensible \u2013 comment l\u2019IA peut-elle vraiment nous aider \u00e0 r\u00e9soudre les Wicked Problems, ces probl\u00e8mes complexes, presque insolubles ?\n\u26a1 Rejoignez-nous pour un serious game unique en son genre et d\u00e9couvrez comment faire face \u00e0 des disruptions massives, tout en utilisant l\u2019IA comme alli\u00e9e ! \ud83d\udd25\n\ud83d\udd0d Ce que vous allez explorer :\n* R\u00e9soudre des Wicked Problems concrets li\u00e9s \u00e0 la disruption des m\u00e9tiers, alors que l\u2019IA devient puissante\u2026 mais parfois impr\u00e9visible.* Naviguer dans un monde BANI, o\u00f9 chaque d\u00e9cision est influenc\u00e9e par la fragilit\u00e9, l\u2019anxi\u00e9t\u00e9 et l\u2019incompr\u00e9hensibilit\u00e9 de notre \u00e9poque.* Transformer ces d\u00e9fis complexes en opportunit\u00e9s, plut\u00f4t qu\u2019en obstacles.* Vivre une exp\u00e9rience fun et ludique, o\u00f9 chaque minute apporte une nouvelle disruption\u2026 vous n\u2019\u00eates jamais au bout de vos surprises !\n\ud83e\udde0 Pourquoi participer ?\n* Apprenez \u00e0 collaborer avec l\u2019IA pour surmonter les probl\u00e8mes du futur \u2013 un avant-go\u00fbt de ce qui nous attend dans les d\u00e9cennies \u00e0 venir.* D\u00e9veloppez des comp\u00e9tences de cr\u00e9ativit\u00e9, d\u2019adaptabilit\u00e9 et de collaboration, tout en naviguant dans l\u2019incertitude.* Plongez dans un serious game immersif, amusant, et ax\u00e9 sur la compr\u00e9hension des dynamiques du monde BANI et des outils IA.\n\ud83c\udf08 Pour qui ?Que vous soyez un amateur de technologie, un strat\u00e8ge d\u2019entreprise, ou simplement curieux de voir comment l\u2019IA va transformer notre monde, ce serious game est fait pour vous !\n\ud83d\udcc5 Quand ? Jeudi 7 novembre \u00e0 18h30\ud83d\udccd O\u00f9 ? 44 Rue Barreyre, 33300 Bordeaux\ud83d\udeb6\u200d\u2642\ufe0f Comment venir ? Tram B, arr\u00eat Chartrons. Les cyclistes sont les bienvenus, parking v\u00e9lo dans la cour !\ud83d\udcbb Pensez \u00e0 apporter votre PC ou votre smartphone\n\ud83d\udd17 Inscription gratuite\n\u2728 Bonus convivialit\u00e9 : Apr\u00e8s avoir affront\u00e9 les Wicked Problems et brav\u00e9 le chaos d\u2019un monde BANI, nous conclurons par un moment convivial autour de ce que chacun aura apport\u00e9, pour \u00e9changer sur les solutions cr\u00e9atives que vous aurez d\u00e9velopp\u00e9es \ud83c\udf7b\ud83e\udd64.",
    "community": "serious-gamers-bordeaux",
    "is_online": false,
    "venue": {
      "name": "44 Rue Barreyre",
      "address": "44 Rue Barreyre",
      "city": "Bordeaux",
      "country": "France"
    },
    "location": "44 Rue Barreyre, Bordeaux",
    "rsvp_limit": 20,
    "rsvp_count": 14
  },
  {
    "title": "\ud83c\udf1f L\u2019Art de la ruse \u00e0 travers les 36 Stratag\u00e8mes de Sun Tzu \ud83c\udf1f",
    "date": "2024-09-26T18:30:00",
    "url": "https://www.meetup.com/seriousgamers-bordeaux/events/303328122/",
    "description": "Dans la vie il parait que la strat\u00e9gie est la cl\u00e9 pour atteindre nos objectifs, d\u00e9jouer les pi\u00e8ges et saisir les opportunit\u00e9s.\nMais comment pouvons-nous vraiment explorer l\u2019art subtil de la strat\u00e9gie et apprendre \u00e0 tourner chaque situation \u00e0 notre avantage ? La r\u00e9ponse se trouve peut-\u00eatre dans les 36 stratag\u00e8mes de Sun Tzu, une sagesse ancestrale chinoise \u00e0 appliquer de mani\u00e8re ludique et moderne !\nGr\u00e2ce \u00e0 un atelier seriousgamers, ensemble, nous plongerons dans ces techniques mill\u00e9naires pour d\u00e9couvrir comment les appliquer dans nos vies professionnelles et personnelles. Attendez-vous \u00e0 un m\u00e9lange de r\u00e9flexion, de ruse et de fun o\u00f9 chaque stratag\u00e8me pourra devenir un outil pour ma\u00eetriser vos interactions et am\u00e9liorer vos prises de d\u00e9cision.\n\ud83d\udca1 Ce que nous allons explorer :\n* D\u00e9couvrir et comprendre les 36 stratag\u00e8mes.* Appliquer ces strat\u00e9gies \u00e0 travers des mises en situation.* D\u00e9velopper des techniques pour prendre l\u2019avantage dans des situations complexes\n\ud83c\udf08 Pour Qui ? Cet atelier est ouvert \u00e0 tous, gamers ou strat\u00e8ges en herbe \ud83d\ude0e\n\ud83d\udcc5 Quand ? Jeudi 26 septembre \u00e0 18h30\ud83d\udccd 44 Rue Barreyre, 33300 Bordeaux\ud83d\udeb6\u200d\u2642\ufe0f Comment : Par le Tram B arr\u00eat Chartrons (pour les cyclistes, le v\u00e9lo peut \u00eatre rang\u00e9 dans la cour).\n\ud83d\udd17 Inscription gratuite\n\u2728 Bonus : La soir\u00e9e se terminera par un moment de convivialit\u00e9, o\u00f9 nous pourrons \u00e9changer autour de ce que chacun aura apport\u00e9 et discuter des stratag\u00e8mes que vous aurez appris \u00e0 ma\u00eetriser. \ud83c\udf7b\ud83e\udd64",
    "community": "serious-gamers-bordeaux",
    "is_online": false,
    "venue": {
      "name": "44 Rue Barreyre",
      "address": "44 Rue Barreyre",
      "city": "Bordeaux",
      "country": "France"
    },
    "location": "44 Rue Barreyre, Bordeaux",
    "rsvp_limit": 20,
    "rsvp_count": 14
  },
  {
    "title": "\ud83c\udf1f R\u00e9v\u00e9ler les besoins cach\u00e9s derri\u00e8res nos \u00e9motions",
    "date": "2024-06-20T18:30:00",
    "url": "https://www.meetup.com/seriousgamers-bordeaux/events/301436123/",
    "description": "Dans le monde du travail comme dans la vie, comprendre et exprimer nos \u00e9motions est essentiel pour des interactions positives.\nMais comment pouvons-nous vraiment explorer nos \u00e9motions et comprendre les besoins cach\u00e9s derri\u00e8re elles ? La r\u00e9ponse pourrait bien se trouver dans un jeu de cartes pas comme les autres !\nGr\u00e2ce \u00e0 un atelier seriousgamers. Ensemble, nous utiliserons le jeu de cartes \u201cEmoSense connect\u201d pour r\u00e9v\u00e9ler les dynamiques \u00e9motionnelles qui influencent vos interactions. En identifiant et en comprenant ces \u00e9motions, vous repartirez avec une compr\u00e9hension approfondie de vous-m\u00eame et des autres.\nVenez d\u00e9couvrir comment la communication non-violente et le jeu peuvent devenir des outils puissants pour transformer vos interactions et r\u00e9v\u00e9ler les besoins sous-jacents de vos \u00e9motions. Pr\u00e9parez-vous \u00e0 repartir inspir\u00e9, motiv\u00e9, et arm\u00e9 de connaissances pratiques pour am\u00e9liorer vos relations personnelles et professionnelles !\n\ud83d\udca1 Ce que nous allons explorer :\u2022 Identifier et comprendre les \u00e9motions et les besoins sous-jacents.\u2022 Am\u00e9liorer la qualit\u00e9 de vos interactions gr\u00e2ce \u00e0 la communication non-violente.\u2022 D\u00e9velopper des strat\u00e9gies pour exprimer vos \u00e9motions de mani\u00e8re constructive et positive.\n\ud83c\udf08 Pour Qui ? Cet atelier est ouvert \u00e0 tous \ud83d\ude1b\n\u2728 Bonus : La soir\u00e9e se conclura par un moment de partage convivial, o\u00f9 vous pourrez \u00e9changer avec d\u2019autres passionn\u00e9s sur vos exp\u00e9riences et vos d\u00e9couvertes et partager ce que vous aurez amen\u00e9 \ud83c\udf7a\ud83e\udd64.\n\ud83d\udc7e Seriousement v\u00f4tres",
    "community": "serious-gamers-bordeaux",
    "is_online": false,
    "venue": {
      "name": "44 Rue Barreyre",
      "address": "44 Rue Barreyre",
      "city": "Bordeaux",
      "country": "France"
    },
    "location": "44 Rue Barreyre, Bordeaux",
    "rsvp_limit": 20,
    "rsvp_count": 11
  },
  {
    "title": "Biais cognitifs : Qui sera le plus diabolique ?",
    "date": "2024-05-29T18:30:00",
    "url": "https://www.meetup.com/seriousgamers-bordeaux/events/300994730/",
    "description": "Explorons les biais cognitifs pour concevoir des exp\u00e9riences utilisateur captivantes\n\ud83e\udde0 Nous d\u00e9couvrirons comment les biais cognitifs peuvent se transformer en outils puissants pour manipuler doucement nos d\u00e9cisions, aussi bien dans le domaine num\u00e9rique que dans notre quotidien.\nDans le monde du design comme dans la vie, comprendre les m\u00e9canismes sous-jacents \u00e0 nos choix peut \u00eatre la cl\u00e9 pour cr\u00e9er des produits vraiment engageants. Mais comment transformer une simple interaction en une exp\u00e9rience captivante et m\u00e9morable ? La r\u00e9ponse pourrait bien r\u00e9sider dans un jeu de cartes tr\u00e8s sp\u00e9cial !\n\ud83c\udccf Venez explorer l'univers des biais cognitifs sous un nouveau pendant le prochain SeriousGamers Bordeaux #LeRun. D\u00e9couvrons comment chaque biais peut \u00eatre subtilement int\u00e9gr\u00e9 dans la conception de produits et services. En identifiant les biais les plus influents et en d\u00e9battant de leurs applications pratiques, vous repartirez avec une compr\u00e9hension de ces leviers psychologiques puissants.\n\ud83d\udca1 Ce que nous allons explorer :\n* Identifier les biais cognitifs cl\u00e9s et leur influence sur le comportement des utilisateurs.* Comprendre comment manipuler (\u00e9thiquement) ces biais pour am\u00e9liorer l'engagement et la satisfaction.* D\u00e9finir des strat\u00e9gies pour utiliser ces connaissances dans vos projets de conception ou de d\u00e9veloppement produit.\n\ud83c\udf08 Pour Qui ? Cet atelier est ouvert \u00e0 tous \u2013 designers, product owner, chefs de produit, marketers, psychologues, \u00e9tudiants, et toute personne curieuse de comprendre les rouages de l'esprit humain \ud83d\ude1b\n\u2728 Bonus : La soir\u00e9e se conclura par un moment de partage convivial, o\u00f9 vous pourrez \u00e9changer avec d'autres passionn\u00e9s sur vos d\u00e9couvertes et partager ce que vous aurez appris \ud83c\udf7a\ud83e\udd64.\n\ud83d\udc41\ufe0f\u200d\ud83d\udde8\ufe0f S\u00e9riousement v\u00f4tres",
    "community": "serious-gamers-bordeaux",
    "is_online": false,
    "venue": {
      "name": "44 Rue Barreyre",
      "address": "44 Rue Barreyre",
      "city": "Bordeaux",
      "country": "France"
    },
    "location": "44 Rue Barreyre, Bordeaux",
    "rsvp_limit": 24,
    "rsvp_count": 23
  },
  {
    "title": "\ud83c\udf1f Forgez une super \u00e9quipe : Un voyage au c\u0153ur de votre \u00e9quipe",
    "date": "2024-04-11T18:30:00",
    "url": "https://www.meetup.com/seriousgamers-bordeaux/events/299889329/",
    "description": "Venez d\u00e9couvrir comment le jeu peut devenir un outil puissant pour accompagner votre \u00e9quipe et d\u00e9bloquer son potentiel. Pr\u00e9parez-vous \u00e0 repartir inspir\u00e9, motiv\u00e9, et arm\u00e9 de connaissances pratiques pour \u00e9lever votre \u00e9quipe vers de nouveaux sommets !\nDans le monde du travail comme dans la vie, la synergie d'\u00e9quipe est la cl\u00e9 du succ\u00e8s. Mais comment transformer un groupe d'individus en une super \u00e9quipe soud\u00e9e et performante ? La r\u00e9ponse pourrait bien se trouver dans un jeu de cartes pas comme les autres !\n\ud83c\udccf Venez explorer le fonctionnement d'une \u00e9quipe sous un nouveau jour gr\u00e2ce \u00e0 un atelier seriousgamers. Ensemble, nous utiliserons un jeu de cartes con\u00e7u par Alexandre Boutin et Patrick Pouchot pour r\u00e9v\u00e9ler les forces et faiblesses de chaque membre de votre \u00e9quipe. En identifiant les r\u00f4les cl\u00e9s et en d\u00e9battant des strat\u00e9gies d'am\u00e9lioration, vous repartirez avec une compr\u00e9hension approfondie des dynamiques \u00e0 l'\u0153uvre au sein de votre groupe.\n\ud83d\udca1 Ce que nous allons explorer :\n* Identifier les forces et les points d'am\u00e9lioration individuels et collectifs.* Comprendre le r\u00f4le et l'impact de chaque membre au sein de l'\u00e9quipe.* D\u00e9finir des actions pour renforcer la coh\u00e9sion et la performance d'une \u00e9quipe.\n\ud83c\udf08 Pour Qui ? Cet atelier est ouvert \u00e0 tous \ud83d\ude1b\n\ud83d\udd17 Inscription gratuite\n\u2728 Bonus : La soir\u00e9e se conclura par un moment de partage convivial, o\u00f9 vous pourrez \u00e9changer avec d'autres passionn\u00e9s sur vos exp\u00e9riences et vos d\u00e9couvertes et partager ce que vous aurez amen\u00e9 \ud83c\udf7a\ud83e\udd64.\n\ud83d\udc7e Seriousement v\u00f4tres\n#SeriousGame #Bordeaux #TeamBuilding #Meetup #SuperEquipe",
    "community": "serious-gamers-bordeaux",
    "is_online": false,
    "venue": {
      "name": "44 Rue Barreyre",
      "address": "44 Rue Barreyre",
      "city": "Bordeaux",
      "country": "France"
    },
    "location": "44 Rue Barreyre, Bordeaux",
    "rsvp_limit": 20,
    "rsvp_count": 15
  },
  {
    "title": "\ud83c\udf1f Seriousgamers Bordeaux : Lib\u00e9rez-vous des d\u00e9pendances inutiles ! #LERUN \u26d3\ufe0f",
    "date": "2024-03-05T18:30:00",
    "url": "https://www.meetup.com/seriousgamers-bordeaux/events/299309570/",
    "description": "Pr\u00eat \u00e0 explorer des strat\u00e9gies pour briser les d\u00e9pendances et renforcer votre autonomie ? Rejoignez-nous pour notre prochain meetup SeriousGamers Bordeaux, ouvert \u00e0 tous les passionn\u00e9s de jeux s\u00e9rieux et d'innovation !\n\ud83d\ude80 Lors de notre prochain meetup, plongeons ensemble dans le monde complexe des d\u00e9pendances et d\u00e9couvrons les outils pratiques pour lib\u00e9rer notre plein potentiel ! L'autonomie se nourrit de d\u00e9pendance, c'est pourquoi nous explorerons les \"Dependency Breakers\" propos\u00e9s par unFIX. Mais rassurez-vous, on ne va pas vous encha\u00eener \u00e0 notre meetup pour l'\u00e9ternit\u00e9 \ud83d\ude09\n\ud83d\udd0d Au programme :\n* Une exploration des concepts de d\u00e9pendances dans nos vies personnelles et professionnelles.* D\u00e9couverte des cartes \"Dependency Breakers\" par unFIX, pour nous aider \u00e0 identifier et contrer efficacement les d\u00e9pendances.* Des sc\u00e9narios pratiques pour prendre en main les \"Dependency Breakers\" et mettre en pratique des strat\u00e9gies adapt\u00e9es.\n\ud83d\udca1 Rejoignez-nous pour une soir\u00e9e conviviale de partage d'exp\u00e9riences et de d\u00e9couverte, d'apprentissage et de fun ! Ensemble, nous explorerons des outils pratiques pour renforcer notre autonomie.\n\u00c0 tr\u00e8s vite \ud83d\udd25\n\ud83d\ude4c Si vous le souhaitez, vous pouvez apporter quelque chose \u00e0 partager pour conclure la soir\u00e9e par un ap\u00e9ro convivial, o\u00f9 chacun pourra partager son exp\u00e9rience avec le groupe !\nSeriousement v\u00f4tres \ud83c\udfaf\ud83d\udc7e",
    "community": "serious-gamers-bordeaux",
    "is_online": false,
    "venue": {
      "name": "44 Rue Barreyre",
      "address": "44 Rue Barreyre",
      "city": "Bordeaux",
      "country": "France"
    },
    "location": "44 Rue Barreyre, Bordeaux",
    "rsvp_limit": 20,
    "rsvp_count": 17
  },
  {
    "title": "\ud83e\uddb4\ud83d\udd25 Explorons les profondeurs de la langue pr\u00e9historique au Conseil de pierre !",
    "date": "2024-02-06T18:30:00",
    "url": "https://www.meetup.com/seriousgamers-bordeaux/events/298714007/",
    "description": "Pr\u00e9parez-vous \u00e0 une aventure sensorielle unique lors de notre prochain meetup \"L'importance de la terminologie\" !\nImaginez ! Nous sommes projet\u00e9s plusieurs milliers d'ann\u00e9es en arri\u00e8re, assis sur des peaux de b\u00eates, au c\u0153ur d'une grotte pr\u00e9historique. En tant que tribu\ud83d\udeb6\u200d\u2642\ufe0f\ud83e\uddd4\ud83c\udffd\u200d\u2642\ufe0f\ud83e\uddb4\ud83c\udf32, nous sommes confront\u00e9s \u00e0 des d\u00e9cisions cruciales telles que la guerre, le mariage, les r\u00e9coltes... tout cela avec un vocabulaire limit\u00e9 \u00e0 18 mots ! \ud83c\udf3f C'est ici que commence notre aventure primitive ! \ud83c\udff9\n**Qui peut participer ?**\nVous, et cinq autres compagnons intr\u00e9pides de l'imaginaire, accompagn\u00e9s de notre Ma\u00eetre du Jeu @solena\n\ud83e\udd69 Rejoignez-nous pour une soir\u00e9e primitive, o\u00f9 la terminologie devient la protagoniste de notre aventure commune ! Invitez vos amis \u00e0 partager cette exp\u00e9rience immersive et \u00e0 se plonger dans un monde o\u00f9 les mots deviennent des outils de pouvoir.\n**Pour s'inscrire** \ud83d\udc49 c'est gratuit\n\ud83c\udff0 O\u00f9 : 44 Rue Barreyre, 33300 Bordeaux\ud83d\udeb6\u200d\u2642\ufe0f Comment : Prenez le Tram B et arr\u00eatez-vous \u00e0 Chartrons (pour les cyclistes, le v\u00e9lo peut \u00eatre rang\u00e9 dans la cour).\ud83e\udd95 Quand : Le mardi 6 f\u00e9vrier 2024\ud83c\udf05 \u00c0 quelle heure : \u00c0 18h30\n\u00c0 tr\u00e8s vite \ud83d\udd25\nPensez \u00e0 apporter quelques os \u00e0 ronger \ud83e\uddb4\ud83e\uddb4 pour conclure la soir\u00e9e par un ap\u00e9ro convivial \ud83c\udf3f\ud83e\udd55\ud83c\udf47 , o\u00f9 chacun pourra partager son exp\u00e9rience avec le groupe ! \ud83c\udf32\ud83c\udff0\ud83c\udf33\nSeriousement v\u00f4tres, l'\u00e9quipe SeriousGamers \ud83d\uddff\ud83d\udeb6\u200d\u2642\ufe0f",
    "community": "serious-gamers-bordeaux",
    "is_online": false,
    "venue": {
      "name": "44 Rue Barreyre",
      "address": "44 Rue Barreyre",
      "city": "Bordeaux",
      "country": "France"
    },
    "location": "44 Rue Barreyre, Bordeaux",
    "rsvp_limit": 8,
    "rsvp_count": 7
  },
  {
    "title": "\ud83d\ude80\ud83d\udd0d Pr\u00eats pour l'Aventure Anti-Sabotage ? Rejoignez-nous ! \ud83d\udd0d\ud83d\ude80",
    "date": "2023-12-05T18:30:00",
    "url": "https://www.meetup.com/seriousgamers-bordeaux/events/297547006/",
    "description": "Chers Aventuriers,\nLoin des films o\u00f9 tout semble si fluide, travailler en \u00e9quipe, c'est une aventure \u00e0 part enti\u00e8re ! \ud83c\udfac Dans notre \u00e9quipe, chaque journ\u00e9e est une exploration avec ses personnages hauts en couleur : Jean-Didier, le ma\u00eetre des r\u00e9unions de crise, Fred le manager aux id\u00e9es impos\u00e9es, et Jean-K\u00e9vin, le champion des discours sans fin en r\u00e9union... un vrai terrain propice au sabotage, n'est-ce pas ?\n**Alors, \u00eates-vous pr\u00eats \u00e0 nous rejoindre lors d'un seriousgame pour \u00e9laborer une strat\u00e9gie d'anti-sabotage ?**\n\ud83c\udfaf **Mission Anti-Sabotage : L'Am\u00e9lioration Continue en Action**\nRejoignez notre meetup Seriousgamers Bordeaux pour d\u00e9couvrir le tout nouveau SG anim\u00e9 par Alain Delachaux, con\u00e7u pour nous aider \u00e0 identifier nos sabotages et surtout \u00e0 d\u00e9velopper des solutions pour les contrer. Un appel \u00e0 l'aide est lanc\u00e9 \u00e0 tous les esprits strat\u00e9giques et les experts de l'am\u00e9lioration continue !\n**Qui peut participer ?**Tout le monde !\nInvitez vos amis passionn\u00e9s \u00e0 se joindre \u00e0 nous pour cette exp\u00e9rience unique ! \ud83c\udfae\ud83d\udc65\n\ud83d\udd96\ud83c\udf1fRejoignez-nous pour une soir\u00e9e o\u00f9 l'aventure de l'anti-sabotage nous m\u00e8nera vers de nouvelles d\u00e9couvertes pour une collaboration renforc\u00e9e !\nPensez \u00e0 apporter un petit quelque chose pour conclure la soir\u00e9e par un ap\u00e9ro convivial, o\u00f9 chacun pourra partager son exp\u00e9rience avec le groupe ! \ud83c\udf7b\n\u00c0 tr\u00e8s bient\u00f4t pour des moments de folie et de fun !\nSeriousement v\u00f4tre ! \ud83c\udfaf\ud83d\udc7e",
    "community": "serious-gamers-bordeaux",
    "is_online": false,
    "venue": {
      "name": "44 Rue Barreyre",
      "address": "44 Rue Barreyre",
      "city": "Bordeaux",
      "country": "France"
    },
    "location": "44 Rue Barreyre, Bordeaux",
    "rsvp_limit": 22,
    "rsvp_count": 17
  },
  {
    "title": "#LaFabrik : Explorez le Futur du Recrutement avec un Nouveau Serious Game ! \ud83d\ude80",
    "date": "2023-11-07T18:30:00",
    "url": "https://www.meetup.com/seriousgamers-bordeaux/events/296908673/",
    "description": "Nous avons le plaisir de vous convier \u00e0 une exp\u00e9rience in\u00e9dite lors de notre prochain Meetup SeriousGamers in Bordeaux : la d\u00e9couverte d'un tout nouveau Serious Game d\u00e9di\u00e9 au recrutement ! Accompagn\u00e9s de l'inspirante Caroline Leleu, cr\u00e9atrice de ce jeu novateur, qui a revisit\u00e9 le concept du Trivial Pursuit pour une approche futuriste et empreinte d'humour du recrutement.\nDans cette aventure, nous mettrons en lumi\u00e8re les Soft Skills, ces comp\u00e9tences intemporelles qui transcendent les \u00e9volutions technologiques, car nous croyons que l'humain est le v\u00e9ritable moteur de la r\u00e9ussite professionnelle.\nAu Programme :\n* Voyagez dans l'histoire captivante de la conception de ce jeu r\u00e9volutionnaire.* Participez \u00e0 une session de jeu, testant ainsi votre adaptabilit\u00e9 et vos comp\u00e9tences.* Partagez vos retours et contribuez \u00e0 faire \u00e9voluer le jeu vers de nouveaux sommets.* Brainstorming pour baptiser ce jeu qui promet de r\u00e9volutionner le monde du recrutement.\nNous avons besoin de vous pour insuffler une bonne dose d'humour et d'\u00e9clat \u00e0 cette exp\u00e9rience !\nAlors, enfilez votre casquette de SeriousGamer de tous horizons et rendez-vous pour une soir\u00e9e o\u00f9 l'avenir du recrutement se dessine sous vos yeux !Invitez vos amis passionn\u00e9s \u00e0 se joindre \u00e0 nous pour cette exp\u00e9rience unique ! \ud83c\udfae\ud83d\udc65\n\ud83d\udccd O\u00f9 : 44 Rue Barreyre, 33300 Bordeaux\ud83d\ude80 Comment : Prenez le Tram B et arr\u00eatez-vous \u00e0 Chartrons (pour les cyclistes, le v\u00e9lo peut \u00eatre rang\u00e9 dans la cour).\ud83d\udcc5 Quand : Le mardi 7 novembre 2023\u23f0 \u00c0 quelle heure : \u00c0 18h30\nC'est gratuit !\nNous conclurons la soir\u00e9e par un ap\u00e9ro convivial, o\u00f9 chacun pourra partager son exp\u00e9rience avec le groupe ! \ud83c\udf7b\n\u00c0 tr\u00e8s bient\u00f4t pour des moments de folie et de fun !\nSeriousement v\u00f4tre ! \ud83d\udd96\ud83c\udf1f",
    "community": "serious-gamers-bordeaux",
    "is_online": false,
    "venue": {
      "name": "44 Rue Barreyre",
      "address": "44 Rue Barreyre",
      "city": "Bordeaux",
      "country": "France"
    },
    "location": "44 Rue Barreyre, Bordeaux",
    "rsvp_limit": 14,
    "rsvp_count": 13
  },
  {
    "title": "Au-del\u00e0 des Guimauves : D\u00e9cortiquons l'utilit\u00e9 des Serious Games \ud83d\ude80\ud83c\udfae",
    "date": "2023-10-03T18:30:00",
    "url": "https://www.meetup.com/seriousgamers-bordeaux/events/296187117/",
    "description": "\u00cates-vous pr\u00eat \u00e0 explorer les m\u00e9andres des Serious Games et \u00e0 d\u00e9voiler leurs secrets les mieux gard\u00e9s ? \ud83e\udd14\ud83d\udd79\ufe0f\nLors de notre prochain meetup, nous mettrons \u00e0 l'\u00e9preuve notre cr\u00e9ativit\u00e9 avec un atelier ludique (ou abrutissant \ud83e\udd14), puis nous plongerons dans une r\u00e9flexion approfondie sur l'utilit\u00e9 (ou non \ud83e\udd14) des Serious Games. \ud83d\udca1\ud83d\udd0d\nD\u00e9couvrons comment ces jeux (s\u00e9rieux ? \ud83e\udd14) peuvent r\u00e9ellement renforcer nos \u00e9quipes et r\u00e9soudre de v\u00e9ritables probl\u00e8mes en entreprise. Nous aborderons \u00e9galement les critiques et les points de vue oppos\u00e9s pour une discussion \u00e9quilibr\u00e9e et informative, et tenterons de r\u00e9fl\u00e9chir s\u00e9rieusement tout en jouant avec de la p\u00e2te molle. \ud83c\udfd7\ufe0f\ud83c\udfe2\nQue vous soyez un novice, curieux ou un expert, pour ou contre les Serious Games, cette rencontre est une opportunit\u00e9 unique pour repenser notre approche de la formation en \u00e9quipe. \ud83d\udcaa\ud83e\udd1d\nRejoignez-nous pour une soir\u00e9e o\u00f9 la r\u00e9flexion et l'innovation se m\u00ealeront \u00e0 l'amusement et \u00e0 la camaraderie. Pr\u00e9parez-vous \u00e0 une aventure intellectuelle dont vous vous souviendrez ! \ud83d\ude80\ud83d\udcad\nUtilisez le hashtag #SeriousGamersBordeaux et invitez vos amis passionn\u00e9s par l'apprentissage ludique \u00e0 se joindre \u00e0 nous pour cette exp\u00e9rience unique ! \ud83c\udfae\ud83d\udc65\n\ud83d\udccd O\u00f9 : 44 Rue Barreyre, 33300 Bordeaux\ud83d\udcc5 Quand : le mardi 3 octobre 2023\u23f0 A quelle heure : \u00e0 18h30\nInscription gratuite\nPr\u00e9parez-vous pour une plong\u00e9e captivante dans l'univers des Serious Games ! \ud83c\udf20\ud83e\udde9\nN'h\u00e9sitez pas \u00e0 partager cette invitation et \u00e0 bloquer la date dans vos agendas. Nous sommes impatients de vous retrouver pour cette soir\u00e9e in\u00e9dite ! \ud83d\ude80\ud83d\udd25\nNous terminerons par un amical ap\u00e9ro avec ce que chacun souhaite partager avec le groupe \ud83c\udf7b\n\u00c0 bient\u00f4t pour des moments de folie et de fun !\nSeriousement v\u00f4tre !",
    "community": "serious-gamers-bordeaux",
    "is_online": false,
    "venue": {
      "name": "44 Rue Barreyre",
      "address": "44 Rue Barreyre",
      "city": "Bordeaux",
      "country": "France"
    },
    "location": "44 Rue Barreyre, Bordeaux",
    "rsvp_limit": 20,
    "rsvp_count": 18
  },
  {
    "title": "Le jeux de r\u00f4le, un outil au service de l'\u00e9quipe - LERUN #8",
    "date": "2023-07-04T18:30:00",
    "url": "https://www.meetup.com/seriousgamers-bordeaux/events/294429317/",
    "description": "\ud83d\ude80\ud83c\udf0c **Rejoignez-nous pour une aventure interstellaire inoubliable !** \ud83c\udf0c\ud83d\ude80\n\u00cates-vous pr\u00eat \u00e0 vous embarquer dans une mission spatiale palpitante en tant que membre de l'\u00e9quipage du vaisseau Le Maraudeur ? \ud83d\ude80\ud83c\udf20\nAu cours de ce prochain meetup, nous explorerons l'incroyable monde du jeu de r\u00f4le et son utilit\u00e9 au sein des \u00e9quipes. \ud83c\udfb2\u2694\ufe0f\nImaginez-vous en tant qu'Alien, andro\u00efde ou humain, et choisissez votre r\u00f4le \u00e0 bord du Maraudeur. \u00cates-vous un expert en diplomatie, un m\u00e9decin chevronn\u00e9 ou un pilote intr\u00e9pide ? \ud83d\udef8\ud83d\udcab\nVotre mission sera de sonder les r\u00e9gions inexplor\u00e9es de l'espace, d\u00e9couvrir de nouvelles civilisations, d\u00e9fendre le Consortium contre les dangers cosmiques, et revenir pour partager vos incroyables aventures avec le reste de l'\u00e9quipage. \ud83c\udf0c\ud83c\udf0d\nRejoignez-nous pour une soir\u00e9e immersive, o\u00f9 collaboration, strat\u00e9gie et imagination se m\u00ealeront dans une exp\u00e9rience unique. \ud83c\udfad\u2728\nQue vous soyez novice ou expert en jeu de r\u00f4le, cette rencontre est ouverte \u00e0 tous ceux qui souhaitent explorer de nouvelles dimensions de la coop\u00e9ration d'\u00e9quipe et vivre des moments de partage inoubliables. \ud83d\udcaa\ud83e\udd1d\nPr\u00e9parez-vous \u00e0 vivre une exp\u00e9rience extraordinaire, o\u00f9 le voyage dans l'espace ne sera qu'une partie de l'aventure. Rejoignez-nous pour ce formidable meetup propos\u00e9 par @Solena \ud83d\ude80\ud83c\udf20\nUtilisez le hashtag #JDRavecleMaraudeur et invitez vos amis passionn\u00e9s par les serious games, l'espace, les jeux de r\u00f4le et l'esprit d'\u00e9quipe \u00e0 se joindre \u00e0 nous pour cette aventure incroyable ! \ud83c\udf1f\ud83d\udc65\n\ud83d\udccd O\u00f9 : 44 Rue Barreyre, 33300 Bordeaux\ud83d\ude80 Comment : Par le Tram B arr\u00eat Chartrons (en v\u00e9lo, possibilit\u00e9 de le rentrer dans la cour)\ud83d\udcc5 Quand : le mardi 4 juillet 2023\u23f0 A quelle heure : \u00e0 18h30\nPr\u00e9parez-vous pour un voyage \u00e9pique dans les \u00e9toiles ! \ud83d\udcab\ud83c\udf1fN'h\u00e9sitez pas \u00e0 partager cette invitation et \u00e0 marquer vos agendas. Nous avons h\u00e2te de vous voir \u00e0 bord du Maraudeur ! \ud83d\ude80\ud83c\udf0c\n#JDRavecleMaraudeur #ExplorationInterstellaire #Espritd\u00c9quipe #Meetup\u00c9pique",
    "community": "serious-gamers-bordeaux",
    "is_online": false,
    "venue": {
      "name": "44 Rue Barreyre",
      "address": "44 Rue Barreyre",
      "city": "Bordeaux",
      "country": "France"
    },
    "location": "44 Rue Barreyre, Bordeaux",
    "rsvp_limit": 12,
    "rsvp_count": 12
  },
  {
    "title": "La vie d'une \u00e9quipe, de sa formation \u00e0 sa dissolution - LERUN #7",
    "date": "2023-06-06T18:30:00",
    "url": "https://www.meetup.com/seriousgamers-bordeaux/events/293761300/",
    "description": "\ud83d\udce3\ud83c\udf89 Annonce sp\u00e9ciale ! Le prochain Meetup \"Seriousgamers Bordeaux\" est en pr\u00e9paration et on a un sujet passionnant \u00e0 vous proposer : \"La vie d'une \u00e9quipe, de sa formation \u00e0 sa dissolution\". \ud83d\udcbc\ud83d\udc65\n\ud83e\udd13 Rejoignez-nous pour une soir\u00e9e pleine d'apprentissage, de jeux (s\u00e9rieux \ud83d\ude1b) et de partage autour de la dynamique des \u00e9quipes. Apr\u00e8s une br\u00e8ve pr\u00e9sentation th\u00e9orique pour poser les bases, nous passerons \u00e0 l'action avec des serious games sur ce th\u00e8me. Et devinez quoi ? C'est vous qui choisissez les jeux que nous explorerons ensemble ! \ud83d\ude2e\ud83c\udfae\n\ud83d\udca5 Que vous soyez manager, leader, membre d'une \u00e9quipe ou simplement curieux de d\u00e9couvrir comment les \u00e9quipes fonctionnent, cette soir\u00e9e est faite pour vous. Venez \u00e9changer vos exp\u00e9riences, rencontrer d'autres passionn\u00e9s et repartir avec des outils concrets pour renforcer votre collaboration. \ud83e\udd1d\ud83d\udca1\n\ud83d\uddd3\ufe0f R\u00e9servez votre place d\u00e8s maintenant pour le mardi 6 juin, car vous ne voudriez pas manquer cette soir\u00e9e riche en d\u00e9couvertes et en fun !\n\ud83c\udf1f Rejoignez la communaut\u00e9 des Seriousgamers, o\u00f9 l'apprentissage rime avec plaisir et o\u00f9 les seriousgame prennent une toute nouvelle dimension. On vous attend nombreux pour une soir\u00e9e inoubliable !\nNous terminerons par un amical ap\u00e9ro avec ce que chacun souhaite partager avec le groupe \ud83c\udf7b\n\u00c0 bient\u00f4t pour des moments de folie et de fun !Seriousement v\u00f4tre !\n\ud83c\udfe1 O\u00f9 : 44 Rue Barreyre, 33300 Bordeaux\ud83d\ude80 Comment : Par le Tram B arr\u00eat Chartrons (en v\u00e9lo, possibilit\u00e9 de le rentrer dans la cour)\ud83c\udfd4 Quand : le mardi 6 juin 2023\u23f0 A quelle heure : \u00e0 18h30\n#Seriousgamers #SeriousGames #Icebreaker #Equipes #Collaboration #Apprentissage #Fun #Partage #Meetup #Bordeaux #team",
    "community": "serious-gamers-bordeaux",
    "is_online": false,
    "venue": {
      "name": "44 Rue Barreyre",
      "address": "44 Rue Barreyre",
      "city": "Bordeaux",
      "country": "France"
    },
    "location": "44 Rue Barreyre, Bordeaux",
    "rsvp_limit": 20,
    "rsvp_count": 14
  },
  {
    "title": "Les \u00e9motions aux commandes - LERUN #6",
    "date": "2023-05-02T18:30:00",
    "url": "https://www.meetup.com/seriousgamers-bordeaux/events/292870423/",
    "description": "Bien le bonjour \u00e0 tous les Serious Gamers !\nLe prochain Meetup \"Seriousgamers Bordeaux\" est d\u00e9j\u00e0 dans les starting-blocks ! Et pour cette sixi\u00e8me \u00e9dition, on va plonger dans le monde des \u00e9motions \ud83c\udfad\nC'est l'occasion pour tous les participants de d\u00e9couvrir comment les \u00e9motions peuvent \u00eatre une ressource. Diana d\u00e9butera la soir\u00e9e par une pr\u00e9sentation fonctionnelle des \u00e9motions, avec un petit exercice pour que tout le monde exp\u00e9rimente. Ensuite, chaque participant pourra faire d\u00e9couvrir au reste du groupe un ice breaker ou un serious game qu'il connait sur les \u00e9motions. \ud83e\udd14\nC'est le moment id\u00e9al pour venir d\u00e9couvrir de nouveaux serious games, rencontrer d'autres passionn\u00e9s et surtout pour s'amuser ensemble ! On vous attend nombreux pour cette soir\u00e9e conviviale et enrichissante le mardi 2 mai. \ud83d\ude0e\nInscription gratuite et obligatoire\nNous terminerons par un amical ap\u00e9ro avec ce que chacun souhaite partager avec le groupe \ud83c\udf7b\n\u00c0 bient\u00f4t pour des moments de folie et de fun !Seriousement v\u00f4tre !\n\ud83c\udfe1 O\u00f9 : 44 Rue Barreyre, 33300 Bordeaux\ud83c\udfd4 Quand : le mardi 2 mai 2023\u23f0 A quelle heure : \u00e0 18h30\n#seriousgamers #seriousGames #Emotions #IceBreaker #Meetup #Bordeaux #Fun #Convivialit\u00e9 #Partage #Apprentissage",
    "community": "serious-gamers-bordeaux",
    "is_online": false,
    "venue": {
      "name": "44 Rue Barreyre",
      "address": "44 Rue Barreyre",
      "city": "Bordeaux",
      "country": "France"
    },
    "location": "44 Rue Barreyre, Bordeaux",
    "rsvp_limit": 20,
    "rsvp_count": 20
  },
  {
    "title": "Devenir les ma\u00eetres dans l'art du feedback - LERUN #5",
    "date": "2023-03-28T18:30:00",
    "url": "https://www.meetup.com/seriousgamers-bordeaux/events/292129611/",
    "description": "Hey les seriousgamers de Bordeaux ! Vous \u00eates pr\u00eats \u00e0 relever un nouveau d\u00e9fi ? \ud83d\ude03\nMardi 28 mars \u00e0 18h30, on vous donne rendez-vous pour une soir\u00e9e plac\u00e9e sous le signe du feedback ! \ud83d\ude4a\ud83d\ude48\ud83d\ude49Au programme : 1h30 de pratique intensive pour devenir les ma\u00eetres dans l'art du feedback. \ud83c\udf93Enfilez votre plus belle tenue de serious gamer et venez nous rejoindre pour cette soir\u00e9e anim\u00e9e par Seriousgamers in Bordeaux LERUN #5. \ud83d\udca5On vous promet une soir\u00e9e ludique et conviviale o\u00f9 vous pourrez d\u00e9velopper vos comp\u00e9tences tout en vous amusant. \ud83d\udcaa\nAlors, partants ? Inscrivez-vous vite, les places sont limit\u00e9es ! \ud83d\ude80\nNous terminerons par un amical ap\u00e9ro avec ce que chacun souhaite partager avec le groupe \ud83c\udf7b\nSeriousement v\u00f4tre !\n\ud83c\udfe1 O\u00f9 : 44 Rue Barreyre, 33300 Bordeaux\ud83d\ude80 Comment : Par le Tram B arr\u00eat Chartrons (en v\u00e9lo, possibilit\u00e9 de le rentrer dans la cours)\ud83c\udfd4 Quand : le mardi 28 mars 2023\u23f0 A quelle heure : \u00e0 18h30",
    "community": "serious-gamers-bordeaux",
    "is_online": false,
    "venue": {
      "name": "44 Rue Barreyre",
      "address": "44 Rue Barreyre",
      "city": "Bordeaux",
      "country": "France"
    },
    "location": "44 Rue Barreyre, Bordeaux",
    "rsvp_limit": 20,
    "rsvp_count": 17
  },
  {
    "title": "SERIOUS GAMERS BORDEAUX LELAB#5 : Testons les liberating structures",
    "date": "2020-04-16T18:00:00",
    "url": "https://www.meetup.com/seriousgamers-bordeaux/events/269968439/",
    "description": "Participez au prochain meetup SeriousGamers Bordeaux depuis chez vous \ud83c\udfe0 ! Et pourquoi pas en famille \ud83d\udc68\u200d\ud83d\udc69\u200d\ud83d\udc67\u200d\ud83d\udc66 ?\nBon \u00e7a va se montrer plus compliqu\u00e9 pour partager le verre \ud83c\udf7b de fin comme on aime tant le faire \ud83d\ude0b !Par contre aucune contrainte pour partager ce verre \ud83c\udf7b tout au long du meetup ! Qui a une bonne recette de cocktail \ud83c\udf79 \u00e0 partager ?\n\ud83d\ude80Alors partant ?Retrouvons nous le 16 Avril \u00e0 18h pour 2 heures de seriousgame.Plut\u00f4t serious \ud83e\udd2a pour le coup et un peut plus facilitation que game.2 heures pour tester des liberating structures, bon pas tout ! Juste 3 ;-)2 heures top chrono pour tenter de r\u00e9pondre \u00e0 la question \u2753 \"Et apr\u00e8s le confinement ?Imaginons, nous sommes fin juin \u26c5, le confinement \ud83d\ude37 est termin\u00e9, un tr\u00e8s bel \u00e9t\u00e9 se pr\u00e9pare \ud83d\ude0e, nous sommes serein.Qu'est ce qui a chang\u00e9 nous permettant d'avoir confiance dans l'avenir \ud83d\ude00 ?\"\n\ud83d\udcc6 Quand : Le 16 avril \u00e0 18h\ud83d\udec1 O\u00f9 : depuis ton canap\u00e9, ton bureau, ton balcon, ton jardin ...\ud83d\udcbb Comment : Nous utiliserons Jitsi et Mural\ud83c\udfa5 Mat\u00e9riel n\u00e9cessaire : un pc, un t\u00e9l\u00e9phone ... avec une cam\u00e9ra, micro etc ... enfin ce que l'on utilise tous en ce momentNombre de participant max : 24, au del\u00e0 nous d\u00e9passons les 2 heures\n\ud83d\udc49 Apr\u00e8s l\u2019inscription merci de communiquer votre email \ud83d\udced en mp afin que je puisse vous inviter sur les diff\u00e9rents outils.\nA tr\u00e8s vite !Portez vous bien",
    "community": "serious-gamers-bordeaux",
    "is_online": true,
    "rsvp_limit": 30,
    "rsvp_count": 26
  },
  {
    "title": "SERIOUS GAMERS BORDEAUX - Pratiquez la Communication Non Violente - LELAB #4",
    "date": "2020-02-05T19:00:00",
    "url": "https://www.meetup.com/seriousgamers-bordeaux/events/268082169/",
    "description": "Bonne ann\u00e9e 2\ufe0f\u20e3\ud83d\ude422\ufe0f\u20e3\ud83d\ude43 \u00e0 toi, oui \ud83d\udc49 toi, joueur \ud83c\udfa1, s\u00e9rieux \ud83e\udd2a seulement ! Pour d\u00e9buter vraiment cette nouvelle ann\u00e9e, #SeriousGamers #Bordeaux t'invite \u00e0 venir tester un serious games sur la th\u00e9matique de la Communication non violante \ud83d\ude24 (#CNV) pendant un meetup #LELAB 4.\nTu souhaites d\u00e9couvrir la CNV ? Avec des coll\u00e8gues \ud83d\udc6c ? En famille \ud83d\udc6a ? Entre amis \ud83d\udc6b ? On compte sur \ud83d\udc49 toi ! Ce sera l'occasion de tester #Con2Col et d'exp\u00e9rimenter physiquement le passage du conflit \ud83e\udd2c \u00e0 la collaboration \ud83e\udd13. Le test de ce SG permettra \u00e9galement aux SeriousGamers Bordeaux, cr\u00e9ateur d'un prototype sur la m\u00eame th\u00e9matique, de l'am\u00e9liorer et de l'aboutir lors d'un nouveau meetup #LAFABRIK.\nMerci \u00e0 Aur\u00e9lie et Charlotte \ud83e\udd29 qui nous accueillent dans les locaux de #Conserto pour ce premier meetup de l'ann\u00e9e.\u2757Attention les places sont limit\u00e9s, ne tardes pas \u00e0 t'inscrire.\n\ud83c\udfe1 O\u00f9 : 185, boulevard du Mar\u00e9chal Leclerc - Le Plaza, B\u00e2timent A\ud83d\ude80 Comment : Par le Tram Chaban Delmas ou en voiture (acc\u00e8s parking sur demande)\ud83c\udfd4 Quand : le 5 f\u00e9vrier 2020\u23f0 A quelle heure : de 19h \u00e0 21h\nNous terminerons comme \u00e0 l'habitude par un ap\u00e9ro \ud83c\udf7b avec ce que tu souhaites partager \ud83c\udf57 avec le groupe \ud83d\udd96\nCon2Col est une cr\u00e9ation #OpenSeriousGame",
    "community": "serious-gamers-bordeaux",
    "is_online": false,
    "venue": {
      "name": "Conserto - Agence de Bordeaux",
      "address": "",
      "city": "Bordeaux",
      "country": "France"
    },
    "location": ", Bordeaux",
    "rsvp_limit": 25,
    "rsvp_count": 25
  },
  {
    "title": "SERIOUS GAMERS BORDEAUX - #LELAB Episode #3",
    "date": "2019-12-17T19:30:00",
    "url": "https://www.meetup.com/seriousgamers-bordeaux/events/266780381/",
    "description": "Le prochain meetup #SeriousGamers aura lieu le mardi 17 D\u00e9cembre et sera accueilli par OASIS COWORKING de 19h30 \u00e0 21h30\nPour cette 3eme \u00e9dition du #LELAB et pour cl\u00f4turer l'ann\u00e9e, nous allons tester de nouveaux #seriousgames.Vous connaissez un serious game et souhaitez le faire d\u00e9couvrir ? C'est le moment ! Rendez vous ici https://docs.google.com/spreadsheets/d/1bRgodh0dq_V4fXkXouaBRyXd5x_U0ocHa5mfej9DKhQ/edit?usp=sharing afin de soumettre les serious game que vous voulez tester et animer.\nLe meetup est ouvert \u00e0 tous !\nNous terminerons par un amical ap\u00e9ro dinatoire o\u00f9 nous partagerons ce que chacun aura apport\u00e9 avec lui.\nSeriousgamement v\u00f4tre !",
    "community": "serious-gamers-bordeaux",
    "is_online": false,
    "venue": {
      "name": "Oasis Coworking - Salles de formation, r\u00e9union, entretien - Bureaux - Open Space",
      "address": "68 Bis Av. Jean Jaur\u00e8s",
      "city": "Cenon",
      "country": "France"
    },
    "location": "68 Bis Av. Jean Jaur\u00e8s, Cenon",
    "rsvp_count": 21
  },
  {
    "title": "SERIOUS GAMERS BORDEAUX - Testons des Serious Games #LELAB Episode #2",
    "date": "2019-10-22T19:00:00",
    "url": "https://www.meetup.com/seriousgamers-bordeaux/events/265507162/",
    "description": "SERIOUS GAMERS BORDEAUX - #LELAB Episode #2\nChers SeriousGamersLe prochain meetup aura lieu le 22 octobre au Node de 19h \u00e0 21h\nComme vous l\u2019avez souhait\u00e9 lors de notre derni\u00e8re rencontre, cette fois-ci nous allons tester des #seriousgames existants.Des serious games que certains d\u2019entre vous connaissent et souhaitent animer et qui r\u00e9pondent aux sujets que vous allez pouvoir proposer d\u00e8s maintenant.\nJ\u2019ouvre d\u00e8s \u00e0 pr\u00e9sent l\u2019inscription au meetup pour nous laisser le temps de recueillir les th\u00e9matiques que vous souhaitez aborder, puis de trouver des serious games adapt\u00e9s avec un animateur qui voudra bien le faciliter.Je vous propose de soumettre vos id\u00e9es dans le fichier suivant : https://docs.google.com/spreadsheets/d/1bRgodh0dq_V4fXkXouaBRyXd5x_U0ocHa5mfej9DKhQ/edit?usp=sharingEt d\u2019y noter \u00e9galement les seriousgames que vous pouvez animer et que vous acceptez de partager avec la communaut\u00e9.\nNous terminerons par un amical ap\u00e9ro dinatoire o\u00f9 nous partagerons ce que chacun aura apport\u00e9 avec lui.\nSeriousgamement v\u00f4tre !",
    "community": "serious-gamers-bordeaux",
    "is_online": false,
    "venue": {
      "name": "Le Node - Aquinum",
      "address": "12 Rue des Faussets",
      "city": "Bordeaux",
      "country": "France"
    },
    "location": "12 Rue des Faussets, Bordeaux",
    "rsvp_count": 21
  },
  {
    "title": "SERIOUS GAMERS BORDEAUX - LELAB Episode #1",
    "date": "2019-09-23T19:00:00",
    "url": "https://www.meetup.com/seriousgamers-bordeaux/events/264517005/",
    "description": "C\u2019est la rentr\u00e9e aussi pour les SeriousGamersProchain meetup le 23 Septembre au Node de 19 \u00e0 21hSERIOUS GAMERS BORDEAUX - LELAB Episode #1\nLors de notre dernier meetup nous avons pu faire progresser 2 prototypes parmi plusieurs cr\u00e9\u00e9s lors du 1er \u00e9pisode LAFABRIK Episode #1- Maitriser nos \u00e9motions avec la CNV- Apprendre \u00e0 innover et penser diff\u00e9remment\nL\u00e9a Lafon et Laurie Ayouaz ont accept\u00e9 d\u2019\u00eatres nos ambassadrices pour repr\u00e9senter ces 2 prototypes de seriousgame et les animer.\nComme promis, pour ce nouveau meetup du lundi 23 septembre au Node de 19 \u00e0 21h nous convions les cr\u00e9ateurs de ces 2 SG pr\u00e9sents aux pr\u00e9c\u00e9dents meetup LAFABRIK Episode #1 et LAFABRIK Episode #2 \u00e0 nous rejoindre pour constater de leur progression et les tester.\nBien sur ce meetup est ouvert \u00e0 tous, m\u00eame ceux qui ne sont jamais venu ! Vous \u00eates tous les bienvenus :-)\nComme pour les 2 pr\u00e9c\u00e9dents meetup, nous terminerons par un amical ap\u00e9ro dinatoire o\u00f9 nous partagerons ce que chacun aura apport\u00e9 avec lui.",
    "community": "serious-gamers-bordeaux",
    "is_online": false,
    "venue": {
      "name": "Le Node - Aquinum",
      "address": "12 Rue des Faussets",
      "city": "Bordeaux",
      "country": "France"
    },
    "location": "12 Rue des Faussets, Bordeaux",
    "rsvp_count": 21
  },
  {
    "title": "SERIOUS GAMERS BORDEAUX - LAFABRIK #2",
    "date": "2019-06-25T19:00:00",
    "url": "https://www.meetup.com/seriousgamers-bordeaux/events/262090300/",
    "description": "Deuxi\u00e8me \u00e9pisode SERIOUS GAMERS BORDEAUX - LAFABRIK #2Lors du pr\u00e9c\u00e9dent \u00e9pisode nous avons cr\u00e9\u00e9 plusieurs prototypes de serious game :- La d\u00e9connexion au quotidien- Prioriser nos t\u00e2ches de tous les jours- Savoir donner un feedback au travers d'un jeux de r\u00f4le- G\u00e9rer nos \u00e9motions- Apprendre \u00e0 innover- Savoir dire non\nEn fonction de la taille du groupe pr\u00e9sent nous s\u00e9lectionnerons deux ou trois jeux \u00e0 \u00e9prouver.\nOuvert \u00e0 tous, viens d\u00e9couvrir toutes les possibilit\u00e9s qu\u2019offrent les Serious Games. Participe \u00e0 leur cr\u00e9ation, ou invente le tiens, et profite de la communaut\u00e9 pour (re)d\u00e9couvrir le pouvoir de transmettre de mani\u00e8re ludique et efficace.\nNous terminerons ce meetup autour d'un ap\u00e9ro, nous vous proposons d'apporter un petit quelque chose \u00e0 manger et/ou \u00e0 boire.\nA tr\u00e8s vite !",
    "community": "serious-gamers-bordeaux",
    "is_online": false,
    "venue": {
      "name": "Le Node - Aquinum",
      "address": "12 Rue des Faussets",
      "city": "Bordeaux",
      "country": "France"
    },
    "location": "12 Rue des Faussets, Bordeaux",
    "rsvp_count": 21
  },
  {
    "title": "SERIOUS GAMERS BORDEAUX - 1h30 pour construire un serious game - LAFABRIK #1",
    "date": "2019-06-04T19:00:00",
    "url": "https://www.meetup.com/seriousgamers-bordeaux/events/261255186/",
    "description": "Pour ce 1er meetup de la communaut\u00e9 SeriousGamers \u00e0 Bordeaux et premier de la s\u00e9rie #LaFabrik, nous t\u2019invitons \u00e0 venir relever le d\u00e9fi de cr\u00e9er un serious game en 1h30.\nNous cr\u00e9erons plusieurs \u00e9quipes qui travailleront sur des th\u00e9matiques diff\u00e9rentes.Chaque \u00e9quipe aura le choix parmi une liste limit\u00e9. Si tu veux pimenter cette liste ou si tu souhaites porter une th\u00e9matique merci de nous la proposer d\u00e8s maintenant.\nOuvert \u00e0 tous, viens d\u00e9couvrir toutes les possibilit\u00e9s qu\u2019offrent les Serious Games. Participe \u00e0 leur cr\u00e9ation, ou invente le tiens, et profite de la communaut\u00e9 pour (re)d\u00e9couvrir le pouvoir de transmettre de mani\u00e8re ludique et efficace.\nEt pour terminer joyeusement ce meetup, nous vous proposons d'apporter quelque chose \u00e0 partager pour un ap\u00e9ro.\nA tr\u00e8s vite !\nL\u2019\u00e9quipe #SeriousGamers",
    "community": "serious-gamers-bordeaux",
    "is_online": false,
    "venue": {
      "name": "Le Node - Aquinum",
      "address": "12 Rue des Faussets",
      "city": "Bordeaux",
      "country": "France"
    },
    "location": "12 Rue des Faussets, Bordeaux",
    "rsvp_count": 39
  }
]
